aiohttp_toolkit/__init__.py
aiohttp_toolkit/_handler.py
aiohttp_toolkit/callback_builders.py
aiohttp_toolkit/response_callbacks.py
aiohttp_toolkit/response_models.py
aiohttp_toolkit/types.py
aiohttp_toolkit-0.1.1.dist-info/LICENSE.txt
aiohttp_toolkit-0.1.1.dist-info/METADATA
aiohttp_toolkit-0.1.1.dist-info/WHEEL
aiohttp_toolkit-0.1.1.dist-info/RECORD
